CHANGES.rst
LICENSE
README.rst
all-requirements.txt
requirements.txt
setup.py
stdeb.cfg
test_settings.py
doc/conf.py
doc/featured.rst
doc/index.rst
doc/readme_from_docstring.py
doc/requirements.txt
doc/settings.rst
doc/themes.rst
doc/views.rst
doc/wsgi.rst
doc/exts/document_init_methods.py
doc/exts/resolve_default_interpreted_role.py
motion/__init__.py
motion/ajax.py
motion/feeds.py
motion/forms.py
motion/models.py
motion/settings.py
motion/tests.py
motion/urls.py
motion/views.py
motion/static/images/compose-content-bg.gif
motion/static/images/compose-header-bg.gif
motion/static/images/compose-on.gif
motion/static/images/dwim_tip_triangle.png
motion/static/images/loadingAnimation.gif
motion/static/images/motion-logo.gif
motion/static/images/nav-current.gif
motion/static/images/search-button.gif
motion/static/images/default-avatars/spaceface-125x125.jpg
motion/static/images/default-avatars/spaceface-250x250.jpg
motion/static/images/default-avatars/spaceface-50x50.jpg
motion/static/images/default-avatars/spaceface-75x75.jpg
motion/static/images/services/aim.png
motion/static/images/services/backtype.png
motion/static/images/services/bebo.png
motion/static/images/services/blogger.png
motion/static/images/services/catster.png
motion/static/images/services/colourlovers.png
motion/static/images/services/corkd.png
motion/static/images/services/deadjournal.png
motion/static/images/services/delicious.png
motion/static/images/services/destructoid.png
motion/static/images/services/digg.png
motion/static/images/services/dodgeball.png
motion/static/images/services/dogster.png
motion/static/images/services/dopplr.png
motion/static/images/services/facebook.png
motion/static/images/services/ffffound.png
motion/static/images/services/flickr.png
motion/static/images/services/fortythreethings.png
motion/static/images/services/friendfeed.png
motion/static/images/services/gametap.png
motion/static/images/services/gblogs.png
motion/static/images/services/gnews.png
typepad_motion.egg-info/PKG-INFO
typepad_motion.egg-info/SOURCES.txt
typepad_motion.egg-info/dependency_links.txt
typepad_motion.egg-info/not-zip-safe
typepad_motion.egg-info/requires.txt
typepad_motion.egg-info/top_level.txt