Metadata-Version: 1.1
Name: typepad-motion
Version: 1.1.2
Summary: Community microblogging in the TypePad cloud
Home-page: http://github.com/sixapart/typepad-motion
Author: Six Apart
Author-email: python@sixapart.com
License: UNKNOWN
Platform: UNKNOWN
Classifier: Development Status :: 4 - Beta
Classifier: Environment :: Console
Classifier: Environment :: Web Environment
Classifier: Framework :: Django
Classifier: Intended Audience :: Developers
Classifier: License :: OSI Approved :: BSD License
Classifier: Operating System :: MacOS :: MacOS X
Classifier: Operating System :: POSIX
Classifier: Programming Language :: Python
Classifier: Topic :: Internet :: WWW/HTTP
Requires: Django(>=1.1.1)
Requires: typepadapp(==1.1.2)
Requires: django_flash(>=1.5.1)
Provides: motion
